ksns/__init__.py
ksns/__main__.py
ksns/cli.py
ksns/client.py
ksns/const.py
ksns-0.0.5.dist-info/LICENSE.md
ksns-0.0.5.dist-info/METADATA
ksns-0.0.5.dist-info/WHEEL
ksns-0.0.5.dist-info/entry_points.txt
ksns-0.0.5.dist-info/top_level.txt
ksns-0.0.5.dist-info/RECORD
