Metadata-Version: 2.1
Name: ksns
Version: 0.0.5
Summary: Switch kubernetes namespace
Home-page: https://github.com/ratulbasak/ksns
Author: Ratul Basak
Author-email: ratulbasak93@gmail.com
License: GPL v3 or later
Keywords: python,kubernetes,namespace,switch namespace,k8s,package
Platform: UNKNOWN
Classifier: Development Status :: 4 - Beta
Classifier: Intended Audience :: Developers
Classifier: Programming Language :: Python :: 3.9
Classifier: Operating System :: Unix
Classifier: Operating System :: MacOS :: MacOS X
Classifier: Operating System :: Microsoft :: Windows
Requires-Dist: click
Requires-Dist: kubernetes
Requires-Dist: PyYAML
Requires-Dist: requests
